README.md
setup.cfg
setup.py
nepal_forex/__init__.py
nepal_forex/conf.py
nepal_forex/datasets.py
nepal_forex/entities.py
nepal_forex/exceptions.py
nepal_forex/nepal_forex.py
nepal_forex.egg-info/PKG-INFO
nepal_forex.egg-info/SOURCES.txt
nepal_forex.egg-info/dependency_links.txt
nepal_forex.egg-info/top_level.txt