Metadata-Version: 2.1
Name: nepal-forex
Version: 1.0
Summary: Nepal ForEx is a Python package for making Currency Exchange easier and fast between NPR and Foreign Currencies.
Home-page: https://github.com/sbishnu019/nepal-forex
Author: Bishnu Sharma
Author-email: sbishnu019@gmail.com
License: UNKNOWN
Download-URL: https://github.com/sbishnu019/nepal-forex/archive/v1.0.tar.gz
Platform: UNKNOWN
Classifier: Programming Language :: Python :: 3
Classifier: License :: OSI Approved :: MIT License
Classifier: Operating System :: OS Independent
Requires-Python: >=3.6
